{
    "products": [
        {
            "id": 1,
            "name": "Laptop",
            "description": "A high-performance laptop suitable for all your computing needs.",
            "price": 999.99,
            "category": "Electronics",
            "stock": 25,
            "rating": 4.5,
            "image": "https://example.com/images/laptop.jpg",
            "features": [
                "16GB RAM",
                "512GB SSD",
                "Intel Core i7",
                "15.6 inch Full HD display"
            ]
        },
        {
            "id": 2,
            "name": "Smartphone",
            "description": "A sleek smartphone with the latest features and technology.",
            "price": 699.99,
            "category": "Electronics",
            "stock": 50,
            "rating": 4.7,
            "image": "https://example.com/images/smartphone.jpg",
            "features": [
                "6.5 inch display",
                "128GB storage",
                "Triple camera setup",
                "Long-lasting battery"
            ]
        },
        {
            "id": 3,
            "name": "Headphones",
            "description": "Wireless headphones with noise cancellation feature.",
            "price": 199.99,
            "category": "Accessories",
            "stock": 75,
            "rating": 4.3,
            "image": "https://example.com/images/headphones.jpg",
            "features": [
                "Active noise cancellation",
                "20 hours battery life",
                "Touch controls",
                "Comfortable fit"
            ]
        },
        {
            "id": 4,
            "name": "Smartwatch",
            "description": "A stylish smartwatch to keep track of your fitness and notifications.",
            "price": 249.99,
            "category": "Wearables",
            "stock": 30,
            "rating": 4.6,
            "image": "https://example.com/images/smartwatch.jpg",
            "features": [
                "Heart rate monitor",
                "GPS tracking",
                "Customizable watch faces",
                "Water-resistant"
            ]
        }
    ]
}